inopyutils/__init__.py
inopyutils/audio_helper.py
inopyutils/config_helper.py
inopyutils/csv_helper.py
inopyutils/file_helper.py
inopyutils/http_helper.py
inopyutils/json_helper.py
inopyutils/log_helper.py
inopyutils/media_helper.py
inopyutils/metadata_meida_helper.py
inopyutils/mongo_helper.py
inopyutils/s3_helper.py
inopyutils/thumbnail_helper.py
inopyutils/util_helper.py
inopyutils-1.5.8.dist-info/licenses/LICENSE
inopyutils-1.5.8.dist-info/METADATA
inopyutils-1.5.8.dist-info/WHEEL
inopyutils-1.5.8.dist-info/top_level.txt
inopyutils-1.5.8.dist-info/RECORD
