Metadata-Version: 2.4
Name: inopyutils
Version: 1.5.8
Summary: A comprehensive Python utility library for S3 storage, media processing, file management, configuration, and logging
Author-email: Inoland <contact@inoland.net>
Project-URL: Homepage, https://github.com/nobandegani/InoPyUtils
Project-URL: Issues, https://github.com/nobandegani/InoPyUtils/issues
Keywords: utilities,s3,media,file-management,logging,configuration
Classifier: Development Status :: 4 - Beta
Classifier: Intended Audience :: Developers
Classifier: License :: OSI Approved :: Mozilla Public License 2.0 (MPL 2.0)
Classifier: Programming Language :: Python :: 3.12
Classifier: Operating System :: OS Independent
Classifier: Topic :: Software Development :: Libraries :: Python Modules
Classifier: Topic :: Utilities
Requires-Python: >=3.9
License-File: LICENSE
Requires-Dist: pillow>=12.0.0
Requires-Dist: pillow_heif>=1.1.1
Requires-Dist: inocloudreve>=0.2.6
Requires-Dist: aioboto3>=15.5.0
Requires-Dist: aiofiles>=25.1.0
Requires-Dist: aiohttp>=3.13.2
Requires-Dist: botocore>=1.39.11
Requires-Dist: boto3>=1.39.11
Requires-Dist: motor>=3.7.1
Dynamic: license-file
